{
  "kind": "collectionType",
  "collectionName": "reviews",
  "info": {
    "singularName": "review",
    "pluralName": "reviews",
    "displayName": "Review",
    "description": "Post-job rating feeding trust_score_yes"
  },
  "options": {
    "draftAndPublish": false
  },
  "pluginOptions": {},
  "attributes": {
    "job": {
      "type": "relation",
      "relation": "manyToOne",
      "target": "api::job.job"
    },
    "from_user": {
      "type": "relation",
      "relation": "manyToOne",
      "target": "plugin::users-permissions.user"
    },
    "to_user": {
      "type": "relation",
      "relation": "manyToOne",
      "target": "plugin::users-permissions.user"
    },
    "rating": {
      "type": "integer",
      "required": true,
      "min": 1,
      "max": 5
    },
    "comment": {
      "type": "text"
    }
  }
}